eventsystem.py
eventsystem-1.1.0.dist-info/WHEEL
eventsystem-1.1.0.dist-info/METADATA
eventsystem-1.1.0.dist-info/RECORD
