Metadata-Version: 2.1
Name: eventsystem
Version: 1.1.0
Summary: Convenient Event System
Keywords: pymitter,event,system
Author-email: baterflyrity <baterflyrity@yandex.ru>
Classifier: Operating System :: OS Independent
Requires-Dist: pymitter >=0.4.0
Project-URL: Bugtracker, https://github.com/baterflyrity/eventsystem/issues
Project-URL: Home, https://pypi.org/project/eventsystem
Project-URL: Sources, https://github.com/baterflyrity/eventsystem
